pycalculator_TomasJ/__init__.py
pycalculator_TomasJ/calculator.py
pycalculator_tomasj-0.1.0.dist-info/METADATA
pycalculator_tomasj-0.1.0.dist-info/WHEEL
pycalculator_tomasj-0.1.0.dist-info/licenses/LICENSE
pycalculator_tomasj-0.1.0.dist-info/RECORD
