Metadata-Version: 2.1
Name: pycalculator_TomasJ
Version: 0.1.0
Summary: A small calculator that performs basic arithmetic with the number in its memory
Project-URL: Homepage, https://github.com/TomasJurkstas/JCalculator
Author-email: Tomas Jurkstas <tomasitassss@gmail.com>
License-File: LICENSE
Classifier: License :: OSI Approved :: MIT License
Classifier: Operating System :: OS Independent
Classifier: Programming Language :: Python :: 3
Requires-Python: >=3.7
